extractcode_libarchive/__init__.py
extractcode_libarchive_system_provided-33.0.0.dist-info/LICENSE.txt
extractcode_libarchive_system_provided-33.0.0.dist-info/METADATA
extractcode_libarchive_system_provided-33.0.0.dist-info/README.rst
extractcode_libarchive_system_provided-33.0.0.dist-info/WHEEL
extractcode_libarchive_system_provided-33.0.0.dist-info/apache-2.0.LICENSE
extractcode_libarchive_system_provided-33.0.0.dist-info/entry_points.txt
extractcode_libarchive_system_provided-33.0.0.dist-info/top_level.txt
extractcode_libarchive_system_provided-33.0.0.dist-info/RECORD
